chromeless/__init__.py
chromeless/__version__.py
chromeless/chromeless.py
chromeless/picklelib.py
chromeless-0.9.1.dist-info/METADATA
chromeless-0.9.1.dist-info/WHEEL
chromeless-0.9.1.dist-info/top_level.txt
chromeless-0.9.1.dist-info/RECORD
