Metadata-Version: 2.1
Name: chromeless
Version: 0.9.1
Summary: Serverless selenium which dynamically execute any given code.
Home-page: https://github.com/umihico/pythonista-chromeless
Author: umihico
Author-email: umihico@users.noreply.github.com
License: UNKNOWN
Platform: UNKNOWN
Classifier: Programming Language :: Python :: 3
Classifier: License :: OSI Approved :: MIT License
Classifier: Operating System :: OS Independent
Requires-Python: >=3.7
Requires-Dist: requests
Requires-Dist: boto3
